thehive5py/__init__.py
thehive5py/main.py
thehive5py/showHelloWorld.py
TheHive5py-0.0.4.dist-info/LICENSE
TheHive5py-0.0.4.dist-info/METADATA
TheHive5py-0.0.4.dist-info/WHEEL
TheHive5py-0.0.4.dist-info/top_level.txt
TheHive5py-0.0.4.dist-info/RECORD
