Metadata-Version: 2.1
Name: TheHive5py
Version: 0.0.4
Summary: Python client for TheHive5
Home-page: https://github.com/Sn0wAlice/TheHive5py
Author: Sn0wAlice
Author-email: snow.alice@pm.me
Project-URL: Bug Tracker, https://github.com/Sn0wAlice/TheHive5py/issues
Project-URL: repository, https://github.com/Sn0wAlice/TheHive5py
Classifier: Development Status :: 4 - Beta
Classifier: Intended Audience :: Developers
Classifier: Intended Audience :: Information Technology
Classifier: Natural Language :: English
Classifier: Programming Language :: Python :: 3.8
Classifier: Programming Language :: Python :: 3.9
Classifier: Programming Language :: Python :: 3.10
Requires-Python: >=3.6
License-File: LICENSE
